{
  "canSurf": false,
  "levelUpMoves": {
    "0": ["Air Slash"],
    "1": [
      "Air Slash",
      "Dragon Claw",
      "Heat Wave",
      "Scratch",
      "Growl",
      "Ember",
      "Smokescreen"
    ],
    "12": ["Dragon Breath"],
    "24": ["Slash"],
    "46": ["Fire Spin"],
    "39": ["Scary Face"],
    "19": ["Fire Fang"],
    "62": ["Flare Blitz"],
    "30": ["Flamethrower"],
    "54": ["Inferno"]
  },
  "tmMoves8": [
    0,
    1,
    3,
    5,
    6,
    8,
    9,
    11,
    13,
    15,
    21,
    22,
    24,
    25,
    26,
    30,
    31,
    34,
    37,
    38,
    39,
    40,
    41,
    43,
    46,
    48,
    59,
    65,
    68,
    76,
    78,
    81,
    92,
    94,
    95,
    97,
    99,
    18,
    32
  ],
  "tmMoves": [
    "Hone Claws",
    "Dragon Claw",
    "Roar",
    "Toxic",
    "Hidden Power",
    "Sunny Day",
    "Hyper Beam",
    "Protect",
    "Roost",
    "Frustration",
    "Solar Beam",
    "Earthquake",
    "Return",
    "Dig",
    "Brick Break",
    "Double Team",
    "Flamethrower",
    "Fire Blast",
    "Rock Tomb",
    "Aerial Ace",
    "Facade",
    "Flame Charge",
    "Rest",
    "Attract",
    "Round",
    "Echoed Voice",
    "Overheat",
    "Steel Wing",
    "Focus Blast",
    "Fling",
    "Sky Drop",
    "Incinerate",
    "Will-O-Wisp",
    "Shadow Claw",
    "Giga Impact",
    "Swords Dance",
    "Bulldoze",
    "Rock Slide",
    "Dragon Tail",
    "Swagger",
    "Substitute",
    "Rock Smash",
    "Cut",
    "Fly",
    "Strength",
    "Defog",
    "Mega Punch",
    "Mega Kick",
    "Body Slam",
    "Take Down",
    "Double-Edge",
    "Submission",
    "Counter",
    "Rage",
    "Dragon Rage",
    "Fissure",
    "Mimic",
    "Bide",
    "Swift",
    "Skull Bash",
    "Dynamic Punch",
    "Headbutt",
    "Curse",
    "Snore",
    "Endure",
    "Iron Tail",
    "Dragon Breath",
    "Mud-Slap",
    "Sleep Talk",
    "Defense Curl",
    "Thunder Punch",
    "Fire Punch",
    "Fury Cutter",
    "Focus Punch",
    "Dragon Pulse",
    "Captivate",
    "Natural Gift",
    "Seismic Toss",
    "Acrobatics",
    "False Swipe",
    "Reflect",
    "Sandstorm",
    "Secret Power",
    "Power-Up Punch",
    "Confide",
    "Work Up",
    "Brutal Swing"
  ],
  "tutorMoves": [
    "Air Cutter",
    "Blast Burn",
    "Block",
    "Fire Pledge",
    "Heat Wave",
    "Ominous Wind",
    "Outrage",
    "Tailwind",
    "Twister",
    "Air Cutter",
    "Air Slash",
    "Beat Up",
    "Belly Drum",
    "Bite",
    "Flare Blitz",
    "Howl",
    "Scary Face",
    "Slash",
    "Inferno",
    "Leer",
    "Hold Hands",
    "Quick Attack",
    "Celebrate",
    "Defog"
  ],
  "catchRate": 45,
  "spawnLevel": 36,
  "abilities": [
    "Blaze",
    null,
    "SolarPower"
  ],
  "eggMoves": [
    "Air Cutter",
    "Beat Up",
    "Belly Drum",
    "Bite",
    "Counter",
    "Crunch",
    "Dragon Dance",
    "Dragon Pulse",
    "Dragon Rush",
    "Flare Blitz",
    "Focus Punch",
    "Metal Claw",
    "Outrage",
    "Ancient Power"
  ],
  "isRideable": true,
  "malePercent": 87,
  "ridingOffsets": {
    "standing": {
      "x": 0,
      "y": -0.5,
      "z": -0.1
    },
    "moving": {
      "x": 0,
      "y": 0,
      "z": 0.3
    }
  },
  "stats": {
    "Speed": 100,
    "HP": 78,
    "SpecialDefence": 85,
    "Attack": 84,
    "SpecialAttack": 109,
    "Defence": 78
  },
  "eggCycles": 21,
  "flyingParameters": {
    "landingMaterials": "LEAVES_AND_GRASS",
    "flyRefreshRateXZ": 100,
    "flyRefreshRateY": 100,
    "flyHeightMin": 0,
    "flightTimeMin": 0,
    "flyHeightMax": 20,
    "flightTimeMax": 20,
    "flapRate": 5,
    "flySpeedModifier": 0.8,
    "flyRefreshRateSpeed": 100
  },
  "spawnLocations": ["Air"],
  "evYields": {"SpecialAttack": 3},
  "evolutions": [],
  "experienceGroup": "MediumSlow",
  "height": 1.7,
  "baseExp": 240,
  "types": [
    "Fire",
    "Flying"
  ],
  "pixelmonName": "Charizard",
  "pokemon": "Charizard",
  "eggGroups": [
    "Monster",
    "Dragon"
  ],
  "preEvolutions": [
    "Charmeleon",
    "Charmander"
  ],
  "length": 0.9,
  "trMoves": [
    0,
    1,
    2,
    10,
    15,
    20,
    24,
    26,
    27,
    31,
    32,
    36,
    41,
    43,
    47,
    51,
    55,
    62,
    64,
    85,
    88,
    89
  ],
  "weight": 90.5,
  "aggression": {
    "timid": 80,
    "aggressive": 20,
    "passive": 0
  },
  "mountedFlying": {
    "maxFlySpeed": 2,
    "turnRate": 1,
    "decelerationRate": 0.3,
    "accelerationRate": 0.05,
    "strafeAccelerationRate": 0.9,
    "upperAngleLimit": 50,
    "lowerAngleLimit": -45,
    "hoverDecelerationRate": 0.07,
    "pitchRate": 1,
    "strafeRollConversion": 30
  },
  "baseFriendship": 70,
  "form": 0,
  "spawnLevelRange": 14,
  "width": 0.9,
  "canFly": true,
  "forms": {
    "1": {
      "abilities": [
        "ToughClaws",
        null,
        null
      ],
      "types": [
        "Fire",
        "Dragon"
      ],
      "ridingOffsets": {
        "standing": {
          "x": 0,
          "y": -0.4,
          "z": -0.6
        },
        "moving": {
          "x": 0,
          "y": -0.6,
          "z": -0.6
        }
      },
      "form": 1,
      "stats": {
        "Speed": 100,
        "HP": 78,
        "SpecialDefence": 85,
        "Attack": 130,
        "SpecialAttack": 130,
        "Defence": 111
      },
      "weight": 110.5
    },
    "2": {
      "abilities": [
        "Drought",
        null,
        null
      ],
      "ridingOffsets": {
        "standing": {
          "x": 0,
          "y": -0.4,
          "z": -0.6
        },
        "moving": {
          "x": 0,
          "y": -0.4,
          "z": -0.6
        }
      },
      "form": 2,
      "stats": {
        "Speed": 100,
        "HP": 78,
        "SpecialDefence": 115,
        "Attack": 104,
        "SpecialAttack": 159,
        "Defence": 78
      },
      "weight": 100.5
    }
  }
}