{
  "canSurf": false,
  "levelUpMoves": {
    "0": ["Thunder Punch"],
    "88": ["Double Iron Bash"],
    "1": [
      "Thunder Punch",
      "Thunder Shock",
      "Harden",
      "Tail Whip",
      "Headbutt"
    ],
    "56": ["Protect"],
    "24": ["Thunder Wave"],
    "48": ["Mega Punch"],
    "80": ["Superpower"],
    "72": ["Dynamic Punch"],
    "40": ["Flash Cannon"],
    "96": ["Hyper Beam"],
    "64": ["Discharge"],
    "32": ["Acid Armor"]
  },
  "tmMoves8": [
    0,
    1,
    4,
    5,
    8,
    9,
    11,
    14,
    20,
    21,
    22,
    24,
    25,
    39,
    43,
    48,
    76,
    90,
    97
  ],
  "tmMoves": [
    "Headbutt",
    "Rest",
    "Protect",
    "Substitute",
    "Facade",
    "Thunder Wave",
    "Rock Slide",
    "Toxic",
    "Ice Punch",
    "Thunderbolt",
    "Thunder",
    "Earthquake",
    "Self-Destruct",
    "Solar Beam",
    "Hyper Beam",
    "Superpower",
    "Flash Cannon",
    "Ice Beam",
    "Mega Punch",
    "Mega Kick",
    "Thunder Punch",
    "Giga Impact",
    "Snore",
    "Brick Break",
    "Rock Tomb",
    "Round",
    "Brutal Swing",
    "Body Slam",
    "Endure",
    "Sleep Talk",
    "Gyro Ball"
  ],
  "tutorMoves": [],
  "catchRate": 3,
  "spawnLevel": 70,
  "abilities": [
    "IronFist",
    null,
    null
  ],
  "eggMoves": [],
  "isRideable": true,
  "malePercent": -1,
  "ridingOffsets": {
    "standing": {
      "x": 0,
      "y": -1,
      "z": 0.2
    },
    "moving": {
      "x": 0,
      "y": -1,
      "z": 0.2
    }
  },
  "stats": {
    "Speed": 34,
    "HP": 135,
    "SpecialDefence": 65,
    "Attack": 143,
    "SpecialAttack": 80,
    "Defence": 143
  },
  "eggCycles": 120,
  "spawnLocations": [],
  "evYields": {"Attack": 3},
  "evolutions": [],
  "experienceGroup": "Slow",
  "height": 2.5,
  "baseExp": 270,
  "types": ["Steel"],
  "pixelmonName": "Melmetal",
  "pokemon": "Melmetal",
  "eggGroups": ["Undiscovered"],
  "preEvolutions": ["Meltan"],
  "length": 2.5,
  "trMoves": [
    1,
    5,
    8,
    9,
    20,
    26,
    27,
    39,
    46,
    52,
    70,
    74,
    79,
    93,
    94,
    99,
    10
  ],
  "weight": 800,
  "aggression": {
    "timid": 100,
    "aggressive": 0,
    "passive": 0
  },
  "baseFriendship": 0,
  "form": -1,
  "spawnLevelRange": 0,
  "width": 2.5,
  "canFly": false,
  "forms": {}
}