{
  "canSurf": false,
  "levelUpMoves": {
    "44": ["Hyper Voice"],
    "12": ["Sing"],
    "24": ["Encore"],
    "36": ["Tickle"],
    "48": ["Last Resort"],
    "16": ["Charm"],
    "28": ["After You"],
    "1": [
      "Pound",
      "Baby-Doll Eyes"
    ],
    "4": ["Helping Hand"],
    "8": ["Echoed Voice"],
    "40": ["Slam"],
    "20": ["Swift"],
    "32": ["Tail Slap"]
  },
  "tmMoves8": [
    14,
    15,
    19,
    21,
    23,
    24,
    25,
    29,
    31,
    33,
    34,
    39,
    40,
    41,
    47,
    56,
    59,
    76,
    79,
    84
  ],
  "tmMoves": [
    "Calm Mind",
    "Toxic",
    "Hidden Power",
    "Sunny Day",
    "Protect",
    "Rain Dance",
    "Safeguard",
    "Frustration",
    "Thunderbolt",
    "Return",
    "Dig",
    "Double Team",
    "Facade",
    "Rest",
    "Attract",
    "Thief",
    "Round",
    "Echoed Voice",
    "Fling",
    "Retaliate",
    "Thunder Wave",
    "Work Up",
    "Grass Knot",
    "Swagger",
    "U-Turn",
    "Substitute",
    "Swift",
    "Snore",
    "Endure",
    "Iron Tail",
    "Mud-Slap",
    "Sleep Talk",
    "Secret Power",
    "Dazzling Gleam",
    "Confide",
    "Shock Wave"
  ],
  "tutorMoves": [
    "After You",
    "Aqua Tail",
    "Covet",
    "Gunk Shot",
    "Helping Hand",
    "Hyper Voice",
    "Knock Off",
    "Last Resort",
    "Seed Bomb",
    "Uproar",
    "Charm",
    "Double Slap",
    "Encore",
    "Flail",
    "Sing",
    "Tickle"
  ],
  "catchRate": 255,
  "spawnLevel": 15,
  "abilities": [
    "CuteCharm",
    "Technician",
    "SkillLink"
  ],
  "eggMoves": [
    "Tail Whip",
    "Aqua Tail",
    "Knock Off",
    "Flail",
    "Endure",
    "Fake Tears",
    "Iron Tail",
    "Mud-Slap",
    "Sleep Talk"
  ],
  "isRideable": false,
  "malePercent": 25,
  "stats": {
    "Speed": 75,
    "HP": 55,
    "SpecialDefence": 40,
    "Attack": 50,
    "SpecialAttack": 40,
    "Defence": 40
  },
  "eggCycles": 16,
  "spawnLocations": ["Land"],
  "evYields": {"Speed": 1},
  "evolutions": [{
    "item": {"itemID": "pixelmon:shiny_stone"},
    "to": {"name": "Cinccino"},
    "conditions": [],
    "evoType": "interact"
  }],
  "experienceGroup": "Fast",
  "height": 0.4,
  "baseExp": 60,
  "types": ["Normal"],
  "pixelmonName": "Minccino",
  "pokemon": "Minccino",
  "eggGroups": ["Field"],
  "preEvolutions": [],
  "length": 0.7,
  "trMoves": [
    8,
    20,
    26,
    27,
    30,
    31,
    35,
    42,
    49,
    59,
    73,
    77,
    85,
    90,
    92
  ],
  "weight": 5.8,
  "aggression": {
    "timid": 80,
    "aggressive": 20,
    "passive": 0
  },
  "baseFriendship": 70,
  "form": 0,
  "spawnLevelRange": 9,
  "width": 0.7,
  "canFly": false,
  "forms": {}
}