{
  "canSurf": true,
  "levelUpMoves": {
    "0": ["Octazooka"],
    "1": [
      "Octazooka",
      "Gunk Shot",
      "Rock Blast",
      "Helping Hand",
      "Water Gun",
      "Wrap",
      "Water Pulse",
      "Focus Energy"
    ],
    "12": ["Psybeam"],
    "24": ["Lock-On"],
    "36": ["Ice Beam"],
    "48": ["Soak"],
    "16": ["Aurora Beam"],
    "30": ["Bullet Seed"],
    "20": ["Bubble Beam"],
    "42": ["Hydro Pump"],
    "54": ["Hyper Beam"]
  },
  "tmMoves8": [
    8,
    9,
    14,
    16,
    21,
    23,
    24,
    25,
    27,
    31,
    33,
    34,
    36,
    39,
    40,
    41,
    45,
    50,
    52,
    53,
    54,
    55,
    57,
    58,
    76
  ],
  "swimmingParameters": {
    "depthRangeStart": 5,
    "swimSpeed": 1.2,
    "depthRangeEnd": 20,
    "refreshRate": 200,
    "decayRate": 0.99
  },
  "tmMoves": [
    "Toxic",
    "Hidden Power",
    "Sunny Day",
    "Ice Beam",
    "Blizzard",
    "Hyper Beam",
    "Protect",
    "Rain Dance",
    "Frustration",
    "Smack Down",
    "Return",
    "Psychic",
    "Double Team",
    "Sludge Wave",
    "Flamethrower",
    "Sludge Bomb",
    "Fire Blast",
    "Facade",
    "Rest",
    "Attract",
    "Thief",
    "Round",
    "Energy Ball",
    "Scald",
    "Charge Beam",
    "Incinerate",
    "Payback",
    "Giga Impact",
    "Thunder Wave",
    "Swagger",
    "Substitute",
    "Flash Cannon",
    "Surf",
    "Waterfall",
    "Dive",
    "Whirlpool",
    "Double-Edge",
    "Bubble Beam",
    "Water Gun",
    "Mimic",
    "Swift",
    "Curse",
    "Snore",
    "Icy Wind",
    "Endure",
    "Mud-Slap",
    "Sleep Talk",
    "Defense Curl",
    "Water Pulse",
    "Bullet Seed",
    "Brine",
    "Captivate",
    "Natural Gift",
    "Seismic Toss",
    "Secret Power",
    "Confide"
  ],
  "tutorMoves": [
    "Bind",
    "Bounce",
    "Gunk Shot",
    "Seed Bomb",
    "Signal Beam",
    "String Shot",
    "Amnesia",
    "Flail",
    "Haze",
    "Hydro Pump",
    "Mist",
    "Octazooka",
    "Focus Energy",
    "Screech"
  ],
  "catchRate": 75,
  "spawnLevel": 25,
  "abilities": [
    "SuctionCups",
    "Sniper",
    "Moody"
  ],
  "eggMoves": [
    "Acid Spray",
    "Aurora Beam",
    "Entrainment",
    "Flail",
    "Haze",
    "Mud Shot",
    "Octazooka",
    "Rock Blast",
    "Screech",
    "Snore",
    "Supersonic",
    "Swift",
    "Water Pulse",
    "Water Spout"
  ],
  "isRideable": false,
  "malePercent": 50,
  "stats": {
    "Speed": 45,
    "HP": 75,
    "SpecialDefence": 75,
    "Attack": 105,
    "SpecialAttack": 105,
    "Defence": 75
  },
  "eggCycles": 21,
  "spawnLocations": ["Water"],
  "evYields": {
    "Attack": 1,
    "SpecialAttack": 1
  },
  "evolutions": [],
  "experienceGroup": "MediumFast",
  "height": 0.9,
  "baseExp": 164,
  "types": ["Water"],
  "pixelmonName": "Octillery",
  "pokemon": "Octillery",
  "eggGroups": [
    "Water1",
    "Water2"
  ],
  "preEvolutions": ["Remoraid"],
  "length": 0.7,
  "trMoves": [
    2,
    3,
    4,
    5,
    6,
    11,
    13,
    15,
    16,
    20,
    22,
    26,
    27,
    59,
    65,
    70,
    73,
    78,
    84,
    98
  ],
  "weight": 28.5,
  "aggression": {
    "timid": 80,
    "aggressive": 20,
    "passive": 0
  },
  "baseFriendship": 70,
  "form": 0,
  "spawnLevelRange": 30,
  "width": 0.7,
  "canFly": false,
  "forms": {}
}