{
  "canSurf": true,
  "levelUpMoves": {
    "0": [
      "Circle Throw",
      "Bubble Beam",
      "Hypnosis",
      "Double Slap",
      "Submission"
    ],
    "53": ["Circle Throw"],
    "32": ["Dynamic Punch"],
    "43": ["Mind Reader"]
  },
  "tmMoves8": [
    35,
    8,
    25,
    33,
    15,
    43,
    48,
    39,
    21,
    31,
    23,
    75,
    76,
    59,
    57,
    9,
    81,
    22,
    45,
    36,
    0,
    1,
    24,
    27,
    4
  ],
  "tmMoves": [
    "Toxic",
    "Hail",
    "Bulk Up",
    "Hidden Power",
    "Ice Beam",
    "Blizzard",
    "Hyper Beam",
    "Protect",
    "Rain Dance",
    "Frustration",
    "Earthquake",
    "Return",
    "Dig",
    "Psychic",
    "Brick Break",
    "Double Team",
    "Rock Tomb",
    "Facade",
    "Rest",
    "Attract",
    "Thief",
    "Low Sweep",
    "Round",
    "Focus Blast",
    "Scald",
    "Fling",
    "Payback",
    "Giga Impact",
    "Bulldoze",
    "Rock Slide",
    "Work Up",
    "Poison Jab",
    "Swagger",
    "Substitute",
    "Rock Smash",
    "Surf",
    "Strength",
    "Waterfall",
    "Dive",
    "Rock Climb",
    "Whirlpool",
    "Mega Punch",
    "Mega Kick",
    "Body Slam",
    "Take Down",
    "Double-Edge",
    "Bubble Beam",
    "Water Gun",
    "Submission",
    "Counter",
    "Rage",
    "Fissure",
    "Mimic",
    "Bide",
    "Metronome",
    "Skull Bash",
    "Psywave",
    "Dynamic Punch",
    "Headbutt",
    "Curse",
    "Snore",
    "Icy Wind",
    "Endure",
    "Mud-Slap",
    "Ice Punch",
    "Sleep Talk",
    "Defense Curl",
    "Detect",
    "Focus Punch",
    "Water Pulse",
    "Captivate",
    "Natural Gift",
    "Seismic Toss",
    "Secret Power",
    "Power-Up Punch",
    "Confide"
  ],
  "tutorMoves": [
    "Endeavor",
    "Helping Hand",
    "Vacuum Wave",
    "Amnesia",
    "Bubble",
    "Double Slap",
    "Encore",
    "Growth",
    "Haze",
    "Hydro Pump",
    "Hypnosis",
    "Lovely Kiss",
    "Mind Reader",
    "Mist",
    "Refresh",
    "Splash",
    "Sweet Kiss",
    "Water Sport",
    "Throat Chop"
  ],
  "catchRate": 45,
  "spawnLevel": 35,
  "abilities": [
    "WaterAbsorb",
    "Damp",
    "SwiftSwim"
  ],
  "eggMoves": [
    "Encore",
    "Endeavor",
    "Endure",
    "Haze",
    "Ice Ball",
    "Mind Reader",
    "Mist",
    "Mud Shot",
    "Refresh",
    "Splash",
    "Water Pulse",
    "Water Sport",
    "Bubble Beam"
  ],
  "isRideable": true,
  "malePercent": 50,
  "ridingOffsets": {"standing": {
    "x": 0,
    "y": -1,
    "z": -0.6
  }},
  "stats": {
    "Speed": 70,
    "HP": 90,
    "SpecialDefence": 90,
    "Attack": 95,
    "SpecialAttack": 70,
    "Defence": 95
  },
  "eggCycles": 21,
  "spawnLocations": ["Land"],
  "evYields": {"Defence": 3},
  "evolutions": [],
  "experienceGroup": "MediumSlow",
  "height": 1.3,
  "baseExp": 185,
  "types": [
    "Water",
    "Fighting"
  ],
  "pixelmonName": "Poliwrath",
  "pokemon": "Poliwrath",
  "eggGroups": ["Water1"],
  "preEvolutions": [
    "Poliwhirl",
    "Poliwag"
  ],
  "length": 0.6,
  "trMoves": [
    48,
    5,
    6,
    10,
    11,
    64,
    84,
    85,
    57,
    20,
    4,
    16,
    1,
    14,
    26,
    27
  ],
  "weight": 54,
  "aggression": {
    "timid": 80,
    "aggressive": 20,
    "passive": 0
  },
  "baseFriendship": 70,
  "form": 0,
  "spawnLevelRange": 15,
  "width": 0.9,
  "canFly": false,
  "forms": {}
}
